google/cloud/version.py
google/cloud/_helpers/__init__.py
google/cloud/_helpers/py.typed
google/cloud/_http/__init__.py
google/cloud/_http/py.typed
google/cloud/_testing/__init__.py
google/cloud/_testing/py.typed
google/cloud/client/__init__.py
google/cloud/client/py.typed
google/cloud/environment_vars/__init__.py
google/cloud/environment_vars/py.typed
google/cloud/exceptions/__init__.py
google/cloud/exceptions/py.typed
google/cloud/obsolete/__init__.py
google/cloud/obsolete/py.typed
google/cloud/operation/__init__.py
google/cloud/operation/py.typed
google_cloud_core-2.4.0.dist-info/LICENSE
google_cloud_core-2.4.0.dist-info/METADATA
google_cloud_core-2.4.0.dist-info/WHEEL
google_cloud_core-2.4.0.dist-info/top_level.txt
google_cloud_core-2.4.0.dist-info/RECORD
